moleditpy_installer/__init__.py
moleditpy_installer/main.py
moleditpy_installer/data/icon.icns
moleditpy_installer/data/icon.ico
moleditpy_installer/data/icon.png
moleditpy_installer-0.1.2.dist-info/METADATA
moleditpy_installer-0.1.2.dist-info/WHEEL
moleditpy_installer-0.1.2.dist-info/entry_points.txt
moleditpy_installer-0.1.2.dist-info/top_level.txt
moleditpy_installer-0.1.2.dist-info/RECORD
