Metadata-Version: 2.4
Name: moleditpy-installer
Version: 0.1.2
Summary: Installer and shortcut creator for moleditpy (OS-dependent)
Author-email: HiroYokoyama <titech.yoko.hiro@gmail.com>
Classifier: Programming Language :: Python :: 3
Classifier: License :: OSI Approved :: Apache Software License
Classifier: Intended Audience :: Science/Research
Classifier: Topic :: Scientific/Engineering :: Chemistry
Classifier: Operating System :: OS Independent
Requires-Python: >=3.9
Requires-Dist: pyshortcuts>=1.0.0
Requires-Dist: moleditpy-linux; sys_platform == "linux"
Requires-Dist: moleditpy; sys_platform == "win32"
Requires-Dist: moleditpy; sys_platform == "darwin"
